scholar_scraper/CustomScholarlyTypes.py
scholar_scraper/ScholarScraper.py
scholar_scraper/__init__.py
scholar_scraper/utilities.py
scholar_scraper-1.0.11.dist-info/LICENSE
scholar_scraper-1.0.11.dist-info/METADATA
scholar_scraper-1.0.11.dist-info/WHEEL
scholar_scraper-1.0.11.dist-info/top_level.txt
scholar_scraper-1.0.11.dist-info/RECORD
