Metadata-Version: 2.1
Name: scholar-scraper
Version: 1.0.11
Summary: A python API to get publications from specific users on Google Scholar.
Home-page: https://github.com/guillaume-elambert/ScholarPythonAPI
Author: Guillaume ELAMBERT
Author-email: guillaume.elambert@yahoo.fr
License: GPLv3+
Keywords: Google Scholar,academics,citations
Classifier: Development Status :: 3 - Alpha
Classifier: Intended Audience :: Developers
Classifier: Intended Audience :: Science/Research
Classifier: Natural Language :: English
Classifier: License :: OSI Approved :: GNU General Public License (GPL)
Classifier: License :: OSI Approved :: GNU General Public License v3 or later (GPLv3+)
Classifier: Operating System :: OS Independent
Classifier: Operating System :: POSIX :: Linux
Classifier: Operating System :: Microsoft :: Windows
Classifier: Operating System :: MacOS :: MacOS X
Classifier: Programming Language :: Python
Classifier: Programming Language :: Python :: 3
Classifier: Programming Language :: Python :: 3 :: Only
Classifier: Topic :: Software Development :: Libraries :: Python Modules
Requires-Python: >=3
License-File: LICENSE
Requires-Dist: scholarly (~=1.7.9)
